fluxio_parser/__init__.py
fluxio_parser/constants.py
fluxio_parser/exceptions.py
fluxio_parser/parser.py
fluxio_parser/resource_decorators.py
fluxio_parser/states/__init__.py
fluxio_parser/states/base.py
fluxio_parser/states/choice.py
fluxio_parser/states/fail.py
fluxio_parser/states/map_.py
fluxio_parser/states/parallel.py
fluxio_parser/states/pass_.py
fluxio_parser/states/succeed.py
fluxio_parser/states/tasks/__init__.py
fluxio_parser/states/tasks/base.py
fluxio_parser/states/tasks/codebuild.py
fluxio_parser/states/tasks/ecs.py
fluxio_parser/states/tasks/ecs_worker.py
fluxio_parser/states/tasks/lambda_function.py
fluxio_parser/states/tasks/lambda_pexpm_runner.py
fluxio_parser/states/tasks/retry.py
fluxio_parser/states/tasks/state_machine.py
fluxio_parser/states/wait.py
fluxio_parser/transformers/__init__.py
fluxio_parser/transformers/data_dict.py
fluxio_parser/transformers/run_method.py
fluxio_parser/transformers/script.py
fluxio_parser/util.py
fluxio_parser/visitors/__init__.py
fluxio_parser/visitors/event_processor.py
fluxio_parser/visitors/script.py
fluxio_parser/visitors/state_machine.py
fluxio_parser/visitors/task.py
fluxio_parser-1.0.0.dist-info/LICENSE.md
fluxio_parser-1.0.0.dist-info/WHEEL
fluxio_parser-1.0.0.dist-info/METADATA
fluxio_parser-1.0.0.dist-info/RECORD
