Metadata-Version: 2.1
Name: fluxio-parser
Version: 1.0.0
Summary: Fluxio parser library
License: BSD-3-Clause
Author: Jonathan Drake
Author-email: jdrake@narrativescience.com
Requires-Python: >=3.8
Classifier: License :: OSI Approved :: BSD License
Classifier: Programming Language :: Python :: 3
Classifier: Programming Language :: Python :: 3.8
Classifier: Programming Language :: Python :: 3.9
Classifier: Programming Language :: Python :: 3.10
Classifier: Programming Language :: Python :: 3.11
Requires-Dist: astor (>=0.8.1,<1)
Requires-Dist: black (>=22.3.0,<23.0.0)
Requires-Dist: networkx (>=2.8.7,<3.0.0)
